dtne/__init__.py
dtne/embedding.py
dtne/utils.py
dtne-0.5.1.dist-info/METADATA
dtne-0.5.1.dist-info/WHEEL
dtne-0.5.1.dist-info/top_level.txt
dtne-0.5.1.dist-info/RECORD
