Metadata-Version: 2.1
Name: dtne
Version: 0.5.1
Summary: Implementation of diffusive topology neighbor embedding
Home-page: https://github.com/statway/dtne
Author: jiangyong Wei
Author-email: weijy026a@outlook.com
Classifier: Programming Language :: Python :: 3
Classifier: License :: OSI Approved :: MIT License
Classifier: Operating System :: OS Independent
Requires-Python: >=3.6
Requires-Dist: numpy
Requires-Dist: scipy
Requires-Dist: scikit-learn
Requires-Dist: matplotlib
